birb.py
birb_keys.py
birb-0.1.0.dist-info/DESCRIPTION.rst
birb-0.1.0.dist-info/METADATA
birb-0.1.0.dist-info/RECORD
birb-0.1.0.dist-info/WHEEL
birb-0.1.0.dist-info/entry_points.txt
birb-0.1.0.dist-info/metadata.json
birb-0.1.0.dist-info/top_level.txt
