Metadata-Version: 2.0
Name: birb
Version: 0.1.0
Summary: Send tweets from your CLI
Home-page: https://github.com/Ovelny/birb
Author: Ovelny
Author-email: this.is.ovelny@gmail.com
License: MIT
Platform: UNKNOWN
Classifier: License :: OSI Approved :: MIT License
Classifier: Environment :: Console
Classifier: Programming Language :: Python :: 3
Requires-Python: >=3
Requires-Dist: twitterAPI
Requires-Dist: click
Requires-Dist: cryptography
